icxcli/__init__.py
icxcli/__main__.py
icxcli/cmd/__init__.py
icxcli/cmd/network_conf.json
icxcli/cmd/wallet.py
icxcli/icx/__init__.py
icxcli/icx/utils.py
icxcli/icx/wallet/__init__.py
icxcli-0.0.4.data/scripts/icli
icxcli-0.0.4.dist-info/METADATA
icxcli-0.0.4.dist-info/RECORD
icxcli-0.0.4.dist-info/WHEEL
icxcli-0.0.4.dist-info/top_level.txt
