Metadata-Version: 2.1
Name: icxcli
Version: 0.0.4
Summary: A Universal Command Line Environment for ICON.
Home-page: https://github.com/icon-project/icon_cli_tool
Author: ICON foundation
Author-email: foo@icon.foundation
License: Apache License 2.0
Platform: UNKNOWN
Classifier: Development Status :: 5 - Production/Stable
Classifier: Intended Audience :: Developers
Classifier: Intended Audience :: System Administrators
Classifier: Natural Language :: English
Classifier: License :: OSI Approved :: Apache Software License
Classifier: Programming Language :: Python
Classifier: Programming Language :: Python :: 3.6
Requires-Dist: requests (>=2.18.4)
Requires-Dist: eth-keyfile (>=0.5.0)
Requires-Dist: secp256k1 (>=0.13.2)
